setup.py
prob_dist_uda/Binomialdistribution.py
prob_dist_uda/Gaussiandistribution.py
prob_dist_uda/Generaldistribution.py
prob_dist_uda/__init__.py
prob_dist_uda.egg-info/PKG-INFO
prob_dist_uda.egg-info/SOURCES.txt
prob_dist_uda.egg-info/dependency_links.txt
prob_dist_uda.egg-info/not-zip-safe
prob_dist_uda.egg-info/top_level.txt